{
    "name": "Jupiter",
    "isPlanet": true,
    "moons": [{
            "moon": "Io",
            "rel": "https://api.le-systeme-solaire.net/rest/bodies/io"
        },
        {
            "moon": "Europe",
            "rel": "https://api.le-systeme-solaire.net/rest/bodies/europe"
        },
        {
            "moon": "Ganymède",
            "rel": "https://api.le-systeme-solaire.net/rest/bodies/ganymede"
        },
        {
            "moon": "Callisto",
            "rel": "https://api.le-systeme-solaire.net/rest/bodies/callisto"
        },
        {
            "moon": "Amalthée",
            "rel": "https://api.le-systeme-solaire.net/rest/bodies/amalthee"
        },
        {
            "moon": "Himalia",
            "rel": "https://api.le-systeme-solaire.net/rest/bodies/himalia"
        },
        {
            "moon": "Élara",
            "rel": "https://api.le-systeme-solaire.net/rest/bodies/elara"
        },
        {
            "moon": "Pasiphaé",
            "rel": "https://api.le-systeme-solaire.net/rest/bodies/pasiphae"
        },
        {
            "moon": "Sinopé",
            "rel": "https://api.le-systeme-solaire.net/rest/bodies/sinope"
        },
        {
            "moon": "Lysithéa",
            "rel": "https://api.le-systeme-solaire.net/rest/bodies/lysithea"
        },
        {
            "moon": "Carmé",
            "rel": "https://api.le-systeme-solaire.net/rest/bodies/carme"
        },
        {
            "moon": "Ananké",
            "rel": "https://api.le-systeme-solaire.net/rest/bodies/ananke"
        },
        {
            "moon": "Léda",
            "rel": "https://api.le-systeme-solaire.net/rest/bodies/leda"
        },
        {
            "moon": "Thébé",
            "rel": "https://api.le-systeme-solaire.net/rest/bodies/thebe"
        },
        {
            "moon": "Adrastée",
            "rel": "https://api.le-systeme-solaire.net/rest/bodies/adrastee"
        },
        {
            "moon": "Métis",
            "rel": "https://api.le-systeme-solaire.net/rest/bodies/metis"
        },
        {
            "moon": "Callirrhoé",
            "rel": "https://api.le-systeme-solaire.net/rest/bodies/callirrhoe"
        },
        {
            "moon": "Thémisto",
            "rel": "https://api.le-systeme-solaire.net/rest/bodies/themisto"
        },
        {
            "moon": "Mégaclité",
            "rel": "https://api.le-systeme-solaire.net/rest/bodies/megaclite"
        },
        {
            "moon": "Taygété",
            "rel": "https://api.le-systeme-solaire.net/rest/bodies/taygete"
        },
        {
            "moon": "Chaldéné",
            "rel": "https://api.le-systeme-solaire.net/rest/bodies/chaldene"
        },
        {
            "moon": "Harpalyké",
            "rel": "https://api.le-systeme-solaire.net/rest/bodies/harpalyke"
        },
        {
            "moon": "Kalyké",
            "rel": "https://api.le-systeme-solaire.net/rest/bodies/kalyke"
        },
        {
            "moon": "Iocasté",
            "rel": "https://api.le-systeme-solaire.net/rest/bodies/iocaste"
        },
        {
            "moon": "Erinomé",
            "rel": "https://api.le-systeme-solaire.net/rest/bodies/erinome"
        },
        {
            "moon": "Isonoé",
            "rel": "https://api.le-systeme-solaire.net/rest/bodies/isonoe"
        },
        {
            "moon": "Praxidyké",
            "rel": "https://api.le-systeme-solaire.net/rest/bodies/praxidike"
        },
        {
            "moon": "Autonoé",
            "rel": "https://api.le-systeme-solaire.net/rest/bodies/autonoe"
        },
        {
            "moon": "Thyoné",
            "rel": "https://api.le-systeme-solaire.net/rest/bodies/thyone"
        },
        {
            "moon": "Hermippé",
            "rel": "https://api.le-systeme-solaire.net/rest/bodies/hermippe"
        },
        {
            "moon": "Aitné",
            "rel": "https://api.le-systeme-solaire.net/rest/bodies/aitne"
        },
        {
            "moon": "Eurydomé",
            "rel": "https://api.le-systeme-solaire.net/rest/bodies/eurydome"
        },
        {
            "moon": "Euanthé",
            "rel": "https://api.le-systeme-solaire.net/rest/bodies/euanthe"
        },
        {
            "moon": "Euporie",
            "rel": "https://api.le-systeme-solaire.net/rest/bodies/euporie"
        },
        {
            "moon": "Orthosie",
            "rel": "https://api.le-systeme-solaire.net/rest/bodies/orthosie"
        },
        {
            "moon": "Spondé",
            "rel": "https://api.le-systeme-solaire.net/rest/bodies/sponde"
        },
        {
            "moon": "Calé",
            "rel": "https://api.le-systeme-solaire.net/rest/bodies/cale"
        },
        {
            "moon": "Pasithée",
            "rel": "https://api.le-systeme-solaire.net/rest/bodies/pasithee"
        },
        {
            "moon": "Hégémone",
            "rel": "https://api.le-systeme-solaire.net/rest/bodies/hegemone"
        },
        {
            "moon": "Mnémé",
            "rel": "https://api.le-systeme-solaire.net/rest/bodies/mneme"
        },
        {
            "moon": "Aoedé",
            "rel": "https://api.le-systeme-solaire.net/rest/bodies/aoede"
        },
        {
            "moon": "Thelxinoé",
            "rel": "https://api.le-systeme-solaire.net/rest/bodies/thelxinoe"
        },
        {
            "moon": "Arché",
            "rel": "https://api.le-systeme-solaire.net/rest/bodies/arche"
        },
        {
            "moon": "Callichore",
            "rel": "https://api.le-systeme-solaire.net/rest/bodies/callichore"
        },
        {
            "moon": "Hélicé",
            "rel": "https://api.le-systeme-solaire.net/rest/bodies/helice"
        },
        {
            "moon": "Carpo",
            "rel": "https://api.le-systeme-solaire.net/rest/bodies/carpo"
        },
        {
            "moon": "Eukéladé",
            "rel": "https://api.le-systeme-solaire.net/rest/bodies/eukelade"
        },
        {
            "moon": "Cyllène",
            "rel": "https://api.le-systeme-solaire.net/rest/bodies/cyllene"
        },
        {
            "moon": "Coré",
            "rel": "https://api.le-systeme-solaire.net/rest/bodies/core"
        },
        {
            "moon": "Hersé",
            "rel": "https://api.le-systeme-solaire.net/rest/bodies/herse"
        },
        {
            "moon": "S/2003 J 2",
            "rel": "https://api.le-systeme-solaire.net/rest/bodies/s2003j2"
        },
        {
            "moon": "Euphémé",
            "rel": "https://api.le-systeme-solaire.net/rest/bodies/eupheme"
        },
        {
            "moon": "S/2003 J 4",
            "rel": "https://api.le-systeme-solaire.net/rest/bodies/s2003j4"
        },
        {
            "moon": "Eiréné",
            "rel": "https://api.le-systeme-solaire.net/rest/bodies/eirene"
        },
        {
            "moon": "S/2003 J 9",
            "rel": "https://api.le-systeme-solaire.net/rest/bodies/s2003j9"
        },
        {
            "moon": "S/2003 J 10",
            "rel": "https://api.le-systeme-solaire.net/rest/bodies/s2003j10"
        },
        {
            "moon": "S/2003 J 12",
            "rel": "https://api.le-systeme-solaire.net/rest/bodies/s2003j12"
        },
        {
            "moon": "Philophrosyne",
            "rel": "https://api.le-systeme-solaire.net/rest/bodies/philophrosyne"
        },
        {
            "moon": "S/2003 J 16",
            "rel": "https://api.le-systeme-solaire.net/rest/bodies/s2003j16"
        },
        {
            "moon": "S/2003 J 18",
            "rel": "https://api.le-systeme-solaire.net/rest/bodies/s2003j18"
        },
        {
            "moon": "S/2003 J 19",
            "rel": "https://api.le-systeme-solaire.net/rest/bodies/s2003j19"
        },
        {
            "moon": "S/2003 J 23",
            "rel": "https://api.le-systeme-solaire.net/rest/bodies/s2003j23"
        },
        {
            "moon": "Dia",
            "rel": "https://api.le-systeme-solaire.net/rest/bodies/dia"
        },
        {
            "moon": "S/2010 J 1",
            "rel": "https://api.le-systeme-solaire.net/rest/bodies/s2010j1"
        },
        {
            "moon": "S/2010 J 2",
            "rel": "https://api.le-systeme-solaire.net/rest/bodies/s2010j2"
        },
        {
            "moon": "S/2011 J 1",
            "rel": "https://api.le-systeme-solaire.net/rest/bodies/s2011j1"
        },
        {
            "moon": "S/2011 J 2",
            "rel": "https://api.le-systeme-solaire.net/rest/bodies/s2011j2"
        },
        {
            "moon": "S/2017 J 1",
            "rel": "https://api.le-systeme-solaire.net/rest/bodies/s2017j1"
        },
        {
            "moon": "S/2016 J 1",
            "rel": "https://api.le-systeme-solaire.net/rest/bodies/s2016j1"
        },
        {
            "moon": "Valétudo",
            "rel": "https://api.le-systeme-solaire.net/rest/bodies/valetudo"
        },
        {
            "moon": "S/2017 J 2",
            "rel": "https://api.le-systeme-solaire.net/rest/bodies/s2017j2"
        },
        {
            "moon": "S/2017 J 3",
            "rel": "https://api.le-systeme-solaire.net/rest/bodies/s2017j3"
        },
        {
            "moon": "Pandia",
            "rel": "https://api.le-systeme-solaire.net/rest/bodies/pandia"
        },
        {
            "moon": "S/2017 J 5",
            "rel": "https://api.le-systeme-solaire.net/rest/bodies/s2017j5"
        },
        {
            "moon": "S/2017 J 6",
            "rel": "https://api.le-systeme-solaire.net/rest/bodies/s2017j6"
        },
        {
            "moon": "S/2017 J 7",
            "rel": "https://api.le-systeme-solaire.net/rest/bodies/s2017j7"
        },
        {
            "moon": "S/2017 J 8",
            "rel": "https://api.le-systeme-solaire.net/rest/bodies/s2017j8"
        },
        {
            "moon": "S/2017 J 9",
            "rel": "https://api.le-systeme-solaire.net/rest/bodies/s2017j9"
        },
        {
            "moon": "Ersa",
            "rel": "https://api.le-systeme-solaire.net/rest/bodies/ersa"
        }
    ],
    "aroundPlanet": null,
    "discoveredBy": "",
    "discoveryDate": "",
    "mass": {
        "massValue": 1.89819,
        "massExponent": 27
    },
    "perihelion": 740379835,
    "aphelion": 816620000,
    "gravity": 24.79,
    "sideralOrbit": 4332.589,
    "explanation": "Jupiter is most likely the oldest planet in the Solar System. Current models of Solar System formation suggest that Jupiter formed at or beyond the snow line; a distance from the early Sun where the temperature is sufficiently cold for volatiles such as water to condense into solids. It first assembled a large solid core before accumulating its gaseous atmosphere. As a consequence, the core must have formed before the solar nebula began to dissipate after 10 million years. Formation models suggest Jupiter grew to 20 times the mass of the Earth in under a million years. The orbiting mass created a gap in the disk, thereafter slowly increasing to 50 Earth masses in 3–4 million years."

}, 
{
    "name": "Neptune",
    "isPlanet": true,
    "moons": [{
            "moon": "Triton",
            "rel": "https://api.le-systeme-solaire.net/rest/bodies/triton"
        },
        {
            "moon": "Néreïde",
            "rel": "https://api.le-systeme-solaire.net/rest/bodies/nereide"
        },
        {
            "moon": "Naïade",
            "rel": "https://api.le-systeme-solaire.net/rest/bodies/naiade"
        },
        {
            "moon": "Thalassa",
            "rel": "https://api.le-systeme-solaire.net/rest/bodies/thalassa"
        },
        {
            "moon": "Despina",
            "rel": "https://api.le-systeme-solaire.net/rest/bodies/despina"
        },
        {
            "moon": "Galatée",
            "rel": "https://api.le-systeme-solaire.net/rest/bodies/galatee"
        },
        {
            "moon": "Larissa",
            "rel": "https://api.le-systeme-solaire.net/rest/bodies/larissa"
        },
        {
            "moon": "Protée",
            "rel": "https://api.le-systeme-solaire.net/rest/bodies/protee"
        },
        {
            "moon": "Halimède",
            "rel": "https://api.le-systeme-solaire.net/rest/bodies/halimede"
        },
        {
            "moon": "Psamathée",
            "rel": "https://api.le-systeme-solaire.net/rest/bodies/psamathee"
        },
        {
            "moon": "Sao",
            "rel": "https://api.le-systeme-solaire.net/rest/bodies/sao"
        },
        {
            "moon": "Laomédie",
            "rel": "https://api.le-systeme-solaire.net/rest/bodies/laomedie"
        },
        {
            "moon": "Néso",
            "rel": "https://api.le-systeme-solaire.net/rest/bodies/neso"
        },
        {
            "moon": "Hippocampe",
            "rel": "https://api.le-systeme-solaire.net/rest/bodies/hippocampe"
        }
    ],
    "aroundPlanet": null,
    "discoveredBy": "Urbain Le Verrier, John Couch Adams, Johann Galle",
    "discoveryDate": "23/09/1846",
    "mass": {
        "massValue": 1.02413,
        "massExponent": 26
    },
    "perihelion": 4459753056,
    "aphelion": 4537039826,
    "gravity": 11.15,
    "sideralOrbit": 60189.0,
    "explanation": "Neptune is the eighth and farthest known Solar planet from the Sun. In the Solar System, it is the fourth-largest planet by diameter, the third-most-massive planet, and the densest giant planet. It is 17 times the mass of Earth, slightly more massive than its near-twin Uranus. Neptune is denser and physically smaller than Uranus because its greater mass causes more gravitational compression of its atmosphere. The planet orbits the Sun once every 164.8 years at an average distance of 30.1 AU (4.5 billion km; 2.8 billion mi). It is named after the Roman god of the sea and has the astronomical symbol ♆, a stylised version of the god Neptune's trident."
}, {

    "name": "Pluto",
    "isPlanet": true,
    "moons": [{
            "moon": "Charon",
            "rel": "https://api.le-systeme-solaire.net/rest/bodies/charon"
        },
        {
            "moon": "Nix",
            "rel": "https://api.le-systeme-solaire.net/rest/bodies/nix"
        },
        {
            "moon": "Hydra",
            "rel": "https://api.le-systeme-solaire.net/rest/bodies/hydra"
        },
        {
            "moon": "Kerberos",
            "rel": "https://api.le-systeme-solaire.net/rest/bodies/kerberos"
        },
        {
            "moon": "Styx",
            "rel": "https://api.le-systeme-solaire.net/rest/bodies/styx"
        }
    ],
    "aroundPlanet": null,
    "discoveredBy": "Clyde W. Tombaugh",
    "discoveryDate": "18/02/1930",
    "mass": {
        "massValue": 1.303,
        "massExponent": 22
    },
    "perihelion": 4436756954,
    "aphelion": 7376124302,
    "gravity": 0.62,
    "sideralOrbit": 90465.0,
    "explanation":"Pluto (minor planet designation: 134340 Pluto) is a dwarf planet in the Kuiper belt, a ring of bodies beyond the orbit of Neptune. It was the first and the largest Kuiper belt object to be discovered. After Pluto was discovered in 1930, it was declared to be the ninth planet from the Sun. Beginning in the 1990s, its status as a planet was questioned following the discovery of several objects of similar size in the Kuiper belt and the scattered disc, including the dwarf planet Eris. This led the International Astronomical Union (IAU) in 2006 to formally define the term `planet`—excluding Pluto and reclassifying it as a dwarf planet."
}, {
    "name": "Uranus",
    "isPlanet": true,
    "moons": [{
            "moon": "Ariel",
            "rel": "https://api.le-systeme-solaire.net/rest/bodies/ariel"
        },
        {
            "moon": "Umbriel",
            "rel": "https://api.le-systeme-solaire.net/rest/bodies/umbriel"
        },
        {
            "moon": "Titania",
            "rel": "https://api.le-systeme-solaire.net/rest/bodies/titania"
        },
        {
            "moon": "Obéron",
            "rel": "https://api.le-systeme-solaire.net/rest/bodies/oberon"
        },
        {
            "moon": "Miranda",
            "rel": "https://api.le-systeme-solaire.net/rest/bodies/miranda"
        },
        {
            "moon": "Cordélia",
            "rel": "https://api.le-systeme-solaire.net/rest/bodies/cordelia"
        },
        {
            "moon": "Ophélie",
            "rel": "https://api.le-systeme-solaire.net/rest/bodies/ophelia"
        },
        {
            "moon": "Bianca",
            "rel": "https://api.le-systeme-solaire.net/rest/bodies/bianca"
        },
        {
            "moon": "Cressida",
            "rel": "https://api.le-systeme-solaire.net/rest/bodies/cressida"
        },
        {
            "moon": "Desdémone",
            "rel": "https://api.le-systeme-solaire.net/rest/bodies/desdemona"
        },
        {
            "moon": "Juliette",
            "rel": "https://api.le-systeme-solaire.net/rest/bodies/juliet"
        },
        {
            "moon": "Portia",
            "rel": "https://api.le-systeme-solaire.net/rest/bodies/portia"
        },
        {
            "moon": "Rosalinde",
            "rel": "https://api.le-systeme-solaire.net/rest/bodies/rosalind"
        },
        {
            "moon": "Belinda",
            "rel": "https://api.le-systeme-solaire.net/rest/bodies/belinda"
        },
        {
            "moon": "Puck",
            "rel": "https://api.le-systeme-solaire.net/rest/bodies/puck"
        },
        {
            "moon": "Caliban",
            "rel": "https://api.le-systeme-solaire.net/rest/bodies/caliban"
        },
        {
            "moon": "Sycorax",
            "rel": "https://api.le-systeme-solaire.net/rest/bodies/sycorax"
        },
        {
            "moon": "Prospero",
            "rel": "https://api.le-systeme-solaire.net/rest/bodies/prospero"
        },
        {
            "moon": "Setebos",
            "rel": "https://api.le-systeme-solaire.net/rest/bodies/setebos"
        },
        {
            "moon": "Stephano",
            "rel": "https://api.le-systeme-solaire.net/rest/bodies/stephano"
        },
        {
            "moon": "Trinculo",
            "rel": "https://api.le-systeme-solaire.net/rest/bodies/trinculo"
        },
        {
            "moon": "Francisco",
            "rel": "https://api.le-systeme-solaire.net/rest/bodies/francisco"
        },
        {
            "moon": "Margaret",
            "rel": "https://api.le-systeme-solaire.net/rest/bodies/margaret"
        },
        {
            "moon": "Ferdinand",
            "rel": "https://api.le-systeme-solaire.net/rest/bodies/ferdinand"
        },
        {
            "moon": "Perdita",
            "rel": "https://api.le-systeme-solaire.net/rest/bodies/perdita"
        },
        {
            "moon": "Mab",
            "rel": "https://api.le-systeme-solaire.net/rest/bodies/mab"
        },
        {
            "moon": "Cupid",
            "rel": "https://api.le-systeme-solaire.net/rest/bodies/cupid"
        }
    ],
    "aroundPlanet": null,
    "discoveredBy": "William Herschel",
    "discoveryDate": "13/03/1781",
    "mass": {
        "massValue": 8.68127,
        "massExponent": 25
    },
    "perihelion": 2734998229,
    "aphelion": 3006318143,
    "gravity": 8.87,
    "sideralOrbit": 30685.4,
    "explanation": "Uranus is the seventh planet from the Sun. Its name is a reference to the Greek god of the sky, Uranus, who, according to Greek mythology, was the great-grandfather of Ares (Mars), grandfather of Zeus (Jupiter) and father of Cronus (Saturn). It has the third-largest planetary radius and fourth-largest planetary mass in the Solar System. Uranus is similar in composition to Neptune, and both have bulk chemical compositions which differ from that of the larger gas giants Jupiter and Saturn. For this reason, scientists often classify Uranus and Neptune as 'ice giants' to distinguish them from the other giant planets. Uranus's atmosphere is similar to Jupiter's and Saturn's in its primary composition of hydrogen and helium, but it contains more 'ices' such as water, ammonia, and methane, along with traces of other hydrocarbons. It has the coldest planetary atmosphere in the Solar System, with a minimum temperature of 49 K (−224 °C; −371 °F), and has a complex, layered cloud structure with water thought to make up the lowest clouds and methane the uppermost layer of clouds. The interior of Uranus is mainly composed of ices and rock."
},